{
  "name": "openlierox-wasm",
  "version": "20260717.1",
  "commit": "393f95a0aba1d7238bc409e4e5f15afdba4cd43c",
  "commitShort": "393f95a0a",
  "commitDate": "2026-07-17T14:42:27+02:00",
  "entry": "index.html",
  "engineFiles": [
    "openlierox.js",
    "openlierox.wasm",
    "openlierox.data"
  ],
  "files": [
    "index.html",
    "openlierox.js",
    "openlierox.wasm",
    "openlierox.data",
    "coi-serviceworker.js",
    "coi-serviceworker.LICENSE",
    "manifest.webmanifest",
    "icon-256.png",
    "icon-512.png",
    "_headers",
    ".htaccess",
    "serve.py",
    "run.command"
  ]
}
